decentralized_summarizer/__init__.py
decentralized_summarizer/main.py
decentralized_summarizer/prompts.py
decentralized_summarizer-2025.12.21120929.dist-info/METADATA
decentralized_summarizer-2025.12.21120929.dist-info/WHEEL
decentralized_summarizer-2025.12.21120929.dist-info/top_level.txt
decentralized_summarizer-2025.12.21120929.dist-info/RECORD
