Metadata-Version: 2.4
Name: decentralized-summarizer
Version: 2025.12.21120929
Summary: A new package that processes user input to generate structured summaries of decentralized protocol concepts, such as Polyproto, by extracting key features and benefits. It uses pattern matching to ens
Author-email: decentralized-summarizer <hi@eugene.plus>
License: MIT
Project-URL: Homepage, https://github.com/chigwell/decentralized-summarizer
Requires-Python: >=3.9
Requires-Dist: langchain-llm7>=0.0.0
Requires-Dist: llmatch-messages>=0.0.0
Requires-Dist: langchain-core>=0.3.0
